dss_custom_tools/__init__.py
dss_custom_tools/jupyter_form.py
dss_custom_tools/version.py
dss_custom_tools-0.0.1.dist-info/licenses/LICENSE
dss_custom_tools-0.0.1.dist-info/METADATA
dss_custom_tools-0.0.1.dist-info/WHEEL
dss_custom_tools-0.0.1.dist-info/top_level.txt
dss_custom_tools-0.0.1.dist-info/RECORD
